{
    "1": {
        "mgs_link": "/profile/23187",
        "score": "3228985",
        "roblox_id": 29666286
    },
    "2": {
        "mgs_link": "/profile/31595",
        "score": "1355905",
        "roblox_id": 666358894
    },
    "3": {
        "mgs_link": "/profile/17148",
        "score": "1142838",
        "roblox_id": 3396084431
    },
    "4": {
        "mgs_link": "/profile/31091",
        "score": "437388",
        "roblox_id": 910107664
    },
    "5": {
        "mgs_link": "/profile/19425",
        "score": "423128",
        "roblox_id": 3396114621
    },
    "6": {
        "mgs_link": "/profile/29995",
        "score": "382994",
        "roblox_id": 5178675
    },
    "7": {
        "mgs_link": "/profile/34397",
        "score": "368519",
        "roblox_id": 48565387
    },
    "8": {
        "mgs_link": "/profile/24814",
        "score": "353141",
        "roblox_id": 1946613959
    },
    "9": {
        "mgs_link": "/pro/Magnus77",
        "score": "328215",
        "roblox_id": 4383738707
    },
    "10": {
        "mgs_link": "/profile/26692",
        "score": "276896",
        "roblox_id": 7809686650
    },
    "11": {
        "mgs_link": "/profile/34403",
        "score": "230396",
        "roblox_id": 1079214051
    },
    "12": {
        "mgs_link": "/profile/21431",
        "score": "216425",
        "roblox_id": 30397528
    },
    "13": {
        "mgs_link": "/profile/34402",
        "score": "197084",
        "roblox_id": 1246584213
    },
    "14": {
        "mgs_link": "/profile/31862",
        "score": "162588",
        "roblox_id": 236280233
    },
    "15": {
        "mgs_link": "/profile/15444",
        "score": "161933",
        "roblox_id": null
    },
    "16": {
        "mgs_link": "/profile/9819",
        "score": "153208",
        "roblox_id": null
    },
    "17": {
        "mgs_link": "/profile/11128",
        "score": "152920",
        "roblox_id": null
    },
    "18": {
        "mgs_link": "/profile/30570",
        "score": "143029",
        "roblox_id": 1751807812
    },
    "19": {
        "mgs_link": "/profile/28780",
        "score": "131820",
        "roblox_id": 119404404
    },
    "20": {
        "mgs_link": "/profile/24093",
        "score": "127563",
        "roblox_id": null
    },
    "21": {
        "mgs_link": "/profile/31735",
        "score": "114108",
        "roblox_id": 662990666
    },
    "22": {
        "mgs_link": "/profile/12040",
        "score": "111696",
        "roblox_id": 3222429
    },
    "23": {
        "mgs_link": "/profile/30722",
        "score": "108807",
        "roblox_id": 157886048
    },
    "24": {
        "mgs_link": "/profile/31657",
        "score": "100819",
        "roblox_id": 418574311
    },
    "25": {
        "mgs_link": "/profile/23296",
        "score": "98965",
        "roblox_id": 49445602
    },
    "26": {
        "mgs_link": "",
        "score": "96802",
        "roblox_id": null
    },
    "27": {
        "mgs_link": "/profile/34496",
        "score": "88433",
        "roblox_id": 1751807812
    },
    "28": {
        "mgs_link": "",
        "score": "85814",
        "roblox_id": null
    },
    "29": {
        "mgs_link": "/profile/3231",
        "score": "82411",
        "roblox_id": 1790417412
    },
    "30": {
        "mgs_link": "/profile/30727",
        "score": "75138",
        "roblox_id": 1018180079
    },
    "31": {
        "mgs_link": "/profile/28896",
        "score": "72437",
        "roblox_id": 74642833
    },
    "32": {
        "mgs_link": "/profile/26724",
        "score": "71555",
        "roblox_id": 121403165
    },
    "33": {
        "mgs_link": "/profile/30767",
        "score": "71099",
        "roblox_id": 406804391
    },
    "34": {
        "mgs_link": "/profile/31320",
        "score": "69534",
        "roblox_id": 639181236
    },
    "35": {
        "mgs_link": "/profile/26689",
        "score": "68858",
        "roblox_id": 68220680
    },
    "36": {
        "mgs_link": "/profile/26680",
        "score": "68449",
        "roblox_id": 40642616
    },
    "37": {
        "mgs_link": "/profile/13083",
        "score": "63801",
        "roblox_id": 107354469
    },
    "38": {
        "mgs_link": "/profile/31738",
        "score": "63609",
        "roblox_id": 254693948
    },
    "39": {
        "mgs_link": "/profile/34442",
        "score": "63004",
        "roblox_id": 405894808
    },
    "40": {
        "mgs_link": "/profile/30279",
        "score": "62274",
        "roblox_id": 14953929
    },
    "41": {
        "mgs_link": "/profile/27169",
        "score": "59465",
        "roblox_id": 2028070760
    },
    "42": {
        "mgs_link": "/profile/27168",
        "score": "57586",
        "roblox_id": 407379902
    },
    "43": {
        "mgs_link": "/profile/27074",
        "score": "57565",
        "roblox_id": 73030226
    },
    "44": {
        "mgs_link": "/profile/30721",
        "score": "56807",
        "roblox_id": 841659250
    },
    "45": {
        "mgs_link": "/profile/22468",
        "score": "56511",
        "roblox_id": 275180007
    },
    "46": {
        "mgs_link": "/profile/33483",
        "score": "55427",
        "roblox_id": 817133338
    },
    "47": {
        "mgs_link": "/profile/33902",
        "score": "54013",
        "roblox_id": 1637470692
    },
    "48": {
        "mgs_link": "/profile/27630",
        "score": "52912",
        "roblox_id": 7908621
    },
    "49": {
        "mgs_link": "/profile/8242",
        "score": "51409",
        "roblox_id": 15758354
    },
    "50": {
        "mgs_link": "/profile/34580",
        "score": "50634",
        "roblox_id": 440183421
    },
    "51": {
        "mgs_link": "/profile/31416",
        "score": "50331",
        "roblox_id": 96492309
    },
    "52": {
        "mgs_link": "/profile/32083",
        "score": "50221",
        "roblox_id": 101598208
    },
    "53": {
        "mgs_link": "/profile/26706",
        "score": "49872",
        "roblox_id": 32456653
    },
    "54": {
        "mgs_link": "/profile/31344",
        "score": "46455",
        "roblox_id": 7837172285
    },
    "55": {
        "mgs_link": "/profile/27464",
        "score": "45307",
        "roblox_id": 1578564925
    },
    "56": {
        "mgs_link": "/profile/34000",
        "score": "44515",
        "roblox_id": 3755318470
    },
    "57": {
        "mgs_link": "/profile/29924",
        "score": "43931",
        "roblox_id": 697082407
    },
    "58": {
        "mgs_link": "/profile/34592",
        "score": "42702",
        "roblox_id": 133017244
    },
    "59": {
        "mgs_link": "/profile/27403",
        "score": "42560",
        "roblox_id": 1196407759
    },
    "60": {
        "mgs_link": "/profile/26677",
        "score": "41918",
        "roblox_id": 4931207322
    },
    "61": {
        "mgs_link": "/profile/30723",
        "score": "41076",
        "roblox_id": 1058908271
    },
    "62": {
        "mgs_link": "",
        "score": "40743",
        "roblox_id": null
    },
    "63": {
        "mgs_link": "/profile/25449",
        "score": "39880",
        "roblox_id": 735344329
    },
    "64": {
        "mgs_link": "/profile/28600",
        "score": "39789",
        "roblox_id": 936079657
    },
    "65": {
        "mgs_link": "/profile/32089",
        "score": "38038",
        "roblox_id": 3788135066
    },
    "66": {
        "mgs_link": "/profile/32384",
        "score": "37982",
        "roblox_id": 10469862
    },
    "67": {
        "mgs_link": "/profile/28090",
        "score": "35703",
        "roblox_id": 69612662
    },
    "68": {
        "mgs_link": "/profile/29872",
        "score": "35541",
        "roblox_id": 76417643
    },
    "69": {
        "mgs_link": "/profile/31591",
        "score": "34309",
        "roblox_id": null
    },
    "70": {
        "mgs_link": "/profile/32723",
        "score": "33577",
        "roblox_id": 183574893
    },
    "71": {
        "mgs_link": "/profile/29816",
        "score": "33245",
        "roblox_id": 13078566
    },
    "72": {
        "mgs_link": "/profile/31508",
        "score": "33093",
        "roblox_id": 2026532992
    },
    "73": {
        "mgs_link": "/profile/29644",
        "score": "32643",
        "roblox_id": 34685319
    },
    "74": {
        "mgs_link": "/profile/27075",
        "score": "32200",
        "roblox_id": 41628835
    },
    "75": {
        "mgs_link": "/profile/29620",
        "score": "31729",
        "roblox_id": 4253271952
    },
    "76": {
        "mgs_link": "/profile/29840",
        "score": "29914",
        "roblox_id": 168337801
    },
    "77": {
        "mgs_link": "/profile/33933",
        "score": "28815",
        "roblox_id": 132441653
    },
    "78": {
        "mgs_link": "/profile/22308",
        "score": "28756",
        "roblox_id": 227775444
    },
    "79": {
        "mgs_link": "/profile/30766",
        "score": "27938",
        "roblox_id": 559989880
    },
    "80": {
        "mgs_link": "/profile/27004",
        "score": "27136",
        "roblox_id": 130489002
    },
    "81": {
        "mgs_link": "/profile/26705",
        "score": "26841",
        "roblox_id": 314794478
    },
    "82": {
        "mgs_link": "/profile/24264",
        "score": "26710",
        "roblox_id": 1388020652
    },
    "83": {
        "mgs_link": "/profile/29303",
        "score": "26593",
        "roblox_id": 1837200789
    },
    "84": {
        "mgs_link": "/profile/25452",
        "score": "26429",
        "roblox_id": 1927302226
    },
    "85": {
        "mgs_link": "/profile/28598",
        "score": "25622",
        "roblox_id": 116544395
    },
    "86": {
        "mgs_link": "/profile/29749",
        "score": "25242",
        "roblox_id": 73738796
    },
    "87": {
        "mgs_link": "/profile/31185",
        "score": "24908",
        "roblox_id": 10950770
    },
    "88": {
        "mgs_link": "/profile/26726",
        "score": "24206",
        "roblox_id": 1451793029
    },
    "89": {
        "mgs_link": "/profile/28893",
        "score": "23922",
        "roblox_id": 29722073
    },
    "90": {
        "mgs_link": "/profile/34722",
        "score": "23918",
        "roblox_id": 3838589116
    },
    "91": {
        "mgs_link": "/profile/32115",
        "score": "23883",
        "roblox_id": 1048708065
    },
    "92": {
        "mgs_link": "/profile/26341",
        "score": "23821",
        "roblox_id": 185308795
    },
    "93": {
        "mgs_link": "/profile/27633",
        "score": "23641",
        "roblox_id": 379343212
    },
    "94": {
        "mgs_link": "/profile/32166",
        "score": "23475",
        "roblox_id": 157696723
    },
    "95": {
        "mgs_link": "/profile/34346",
        "score": "22301",
        "roblox_id": 2722467628
    },
    "96": {
        "mgs_link": "/profile/11563",
        "score": "22084",
        "roblox_id": null
    },
    "97": {
        "mgs_link": "/profile/27350",
        "score": "21520",
        "roblox_id": 391114511
    },
    "98": {
        "mgs_link": "/profile/19485",
        "score": "20494",
        "roblox_id": 139816438
    },
    "99": {
        "mgs_link": "/profile/31676",
        "score": "20339",
        "roblox_id": 35433007
    },
    "100": {
        "mgs_link": "/profile/26493",
        "score": "19933",
        "roblox_id": 1015066556
    },
    "101": {
        "mgs_link": "/profile/34676",
        "score": "19501",
        "roblox_id": 3534752556
    },
    "102": {
        "mgs_link": "/profile/304",
        "score": "19485",
        "roblox_id": 1340718761
    },
    "103": {
        "mgs_link": "/profile/28087",
        "score": "19417",
        "roblox_id": 17900059
    },
    "104": {
        "mgs_link": "/profile/31664",
        "score": "19382",
        "roblox_id": 2417445371
    },
    "105": {
        "mgs_link": "/profile/30786",
        "score": "19162",
        "roblox_id": 105233923
    },
    "106": {
        "mgs_link": "/profile/29009",
        "score": "19149",
        "roblox_id": 534312431
    },
    "107": {
        "mgs_link": "/profile/32523",
        "score": "18648",
        "roblox_id": 477579776
    },
    "108": {
        "mgs_link": "/profile/29126",
        "score": "18098",
        "roblox_id": 174716109
    },
    "109": {
        "mgs_link": "/profile/29629",
        "score": "17791",
        "roblox_id": 459983273
    },
    "110": {
        "mgs_link": "/profile/27107",
        "score": "17678",
        "roblox_id": 1561064
    },
    "111": {
        "mgs_link": "/profile/3321",
        "score": "17427",
        "roblox_id": null
    },
    "112": {
        "mgs_link": "/profile/21398",
        "score": "17421",
        "roblox_id": 6147383
    },
    "113": {
        "mgs_link": "/profile/26582",
        "score": "16470",
        "roblox_id": 463758443
    },
    "114": {
        "mgs_link": "/profile/34526",
        "score": "15945",
        "roblox_id": 929628703
    },
    "115": {
        "mgs_link": "/profile/31698",
        "score": "15401",
        "roblox_id": 55575362
    },
    "116": {
        "mgs_link": "/profile/27158",
        "score": "15226",
        "roblox_id": 4213274
    },
    "117": {
        "mgs_link": "/profile/27005",
        "score": "15202",
        "roblox_id": 461657385
    },
    "118": {
        "mgs_link": "/profile/29665",
        "score": "15138",
        "roblox_id": 62908718
    },
    "119": {
        "mgs_link": "/profile/31768",
        "score": "14841",
        "roblox_id": 969808254
    },
    "120": {
        "mgs_link": "/profile/24825",
        "score": "14712",
        "roblox_id": 21711375
    },
    "121": {
        "mgs_link": "/profile/21342",
        "score": "14398",
        "roblox_id": 45284010
    },
    "122": {
        "mgs_link": "/profile/26669",
        "score": "14303",
        "roblox_id": 319438417
    },
    "123": {
        "mgs_link": "/profile/22686",
        "score": "13854",
        "roblox_id": 3841880910
    },
    "124": {
        "mgs_link": "/profile/21815",
        "score": "13488",
        "roblox_id": 86639063
    },
    "125": {
        "mgs_link": "/profile/25203",
        "score": "13339",
        "roblox_id": 77073632
    },
    "126": {
        "mgs_link": "",
        "score": "13264",
        "roblox_id": null
    },
    "127": {
        "mgs_link": "/profile/25043",
        "score": "13259",
        "roblox_id": 1416885032
    },
    "128": {
        "mgs_link": "/profile/28306",
        "score": "13108",
        "roblox_id": 1262689461
    },
    "129": {
        "mgs_link": "/profile/34035",
        "score": "13062",
        "roblox_id": 2560262759
    },
    "130": {
        "mgs_link": "/profile/31814",
        "score": "13047",
        "roblox_id": 2210423641
    },
    "131": {
        "mgs_link": "/profile/31902",
        "score": "12814",
        "roblox_id": 3392129146
    },
    "132": {
        "mgs_link": "/profile/24378",
        "score": "12783",
        "roblox_id": 159604389
    },
    "133": {
        "mgs_link": "/profile/28903",
        "score": "12598",
        "roblox_id": 106079243
    },
    "134": {
        "mgs_link": "/profile/32141",
        "score": "12357",
        "roblox_id": 631474129
    },
    "135": {
        "mgs_link": "/profile/24493",
        "score": "12337",
        "roblox_id": 106620033
    },
    "136": {
        "mgs_link": "/profile/30396",
        "score": "12060",
        "roblox_id": 486004978
    },
    "137": {
        "mgs_link": "/profile/30621",
        "score": "11174",
        "roblox_id": null
    },
    "138": {
        "mgs_link": "/profile/30138",
        "score": "11062",
        "roblox_id": 4613428845
    },
    "139": {
        "mgs_link": "/profile/28561",
        "score": "10789",
        "roblox_id": 107748779
    },
    "140": {
        "mgs_link": "/profile/17434",
        "score": "10492",
        "roblox_id": 22674979
    },
    "141": {
        "mgs_link": "/profile/28554",
        "score": "10409",
        "roblox_id": 1550291658
    },
    "142": {
        "mgs_link": "/profile/26508",
        "score": "10303",
        "roblox_id": 413938595
    },
    "143": {
        "mgs_link": "/profile/32515",
        "score": "10116",
        "roblox_id": 2336725585
    },
    "144": {
        "mgs_link": "/profile/27646",
        "score": "9978",
        "roblox_id": 51264408
    },
    "145": {
        "mgs_link": "/profile/26070",
        "score": "9772",
        "roblox_id": 9307878
    },
    "146": {
        "mgs_link": "",
        "score": "9747",
        "roblox_id": null
    },
    "147": {
        "mgs_link": "/profile/25887",
        "score": "9730",
        "roblox_id": 125045492
    },
    "148": {
        "mgs_link": "/profile/31031",
        "score": "9381",
        "roblox_id": 8163320740
    },
    "149": {
        "mgs_link": "/profile/26785",
        "score": "9287",
        "roblox_id": 1194683697
    },
    "150": {
        "mgs_link": "/profile/29755",
        "score": "9203",
        "roblox_id": 1509600534
    },
    "151": {
        "mgs_link": "/profile/19367",
        "score": "9094",
        "roblox_id": 97220890
    },
    "152": {
        "mgs_link": "/profile/33998",
        "score": "9089",
        "roblox_id": 2350853222
    },
    "153": {
        "mgs_link": "/profile/6980",
        "score": "8971",
        "roblox_id": 119205656
    },
    "154": {
        "mgs_link": "/profile/31966",
        "score": "8678",
        "roblox_id": 4966499367
    },
    "155": {
        "mgs_link": "/profile/32997",
        "score": "8637",
        "roblox_id": 8076708046
    },
    "156": {
        "mgs_link": "/profile/25789",
        "score": "8497",
        "roblox_id": 1276906588
    },
    "157": {
        "mgs_link": "/profile/25672",
        "score": "8324",
        "roblox_id": 126665405
    },
    "158": {
        "mgs_link": "/profile/10389",
        "score": "8193",
        "roblox_id": 21325619
    },
    "159": {
        "mgs_link": "/profile/29771",
        "score": "8129",
        "roblox_id": 3336500555
    },
    "160": {
        "mgs_link": "/profile/28717",
        "score": "8111",
        "roblox_id": 1134337211
    },
    "161": {
        "mgs_link": "/profile/29671",
        "score": "7898",
        "roblox_id": 2409427960
    },
    "162": {
        "mgs_link": "/profile/5668",
        "score": "7677",
        "roblox_id": 689765251
    },
    "163": {
        "mgs_link": "/profile/33626",
        "score": "7551",
        "roblox_id": 761198898
    },
    "164": {
        "mgs_link": "/profile/30475",
        "score": "7295",
        "roblox_id": 19376569
    },
    "165": {
        "mgs_link": "/profile/10942",
        "score": "7189",
        "roblox_id": 131136358
    },
    "166": {
        "mgs_link": "/profile/30116",
        "score": "6951",
        "roblox_id": 1566903128
    },
    "167": {
        "mgs_link": "/profile/27092",
        "score": "6930",
        "roblox_id": 106435459
    },
    "168": {
        "mgs_link": "/profile/24214",
        "score": "6820",
        "roblox_id": null
    },
    "169": {
        "mgs_link": "/profile/29084",
        "score": "6726",
        "roblox_id": 237595971
    },
    "170": {
        "mgs_link": "/profile/24181",
        "score": "6715",
        "roblox_id": 3361194952
    },
    "171": {
        "mgs_link": "/profile/30829",
        "score": "6710",
        "roblox_id": 3973170586
    },
    "172": {
        "mgs_link": "/profile/31484",
        "score": "6660",
        "roblox_id": 89359807
    },
    "173": {
        "mgs_link": "/profile/21903",
        "score": "6554",
        "roblox_id": 666747743
    },
    "174": {
        "mgs_link": "/profile/33878",
        "score": "6525",
        "roblox_id": 5648942107
    },
    "175": {
        "mgs_link": "/profile/28728",
        "score": "6484",
        "roblox_id": 997169479
    },
    "176": {
        "mgs_link": "/profile/33024",
        "score": "6342",
        "roblox_id": 647616678
    },
    "177": {
        "mgs_link": "/profile/34643",
        "score": "6225",
        "roblox_id": 3388820946
    },
    "178": {
        "mgs_link": "/profile/29731",
        "score": "6200",
        "roblox_id": 4331026
    },
    "179": {
        "mgs_link": "",
        "score": "6194",
        "roblox_id": null
    },
    "180": {
        "mgs_link": "/profile/27917",
        "score": "6158",
        "roblox_id": 104952427
    },
    "181": {
        "mgs_link": "/profile/28374",
        "score": "5978",
        "roblox_id": 230816847
    },
    "182": {
        "mgs_link": "/profile/32623",
        "score": "5962",
        "roblox_id": 721024447
    },
    "183": {
        "mgs_link": "/profile/12638",
        "score": "5885",
        "roblox_id": 3834304156
    },
    "184": {
        "mgs_link": "/profile/26516",
        "score": "5849",
        "roblox_id": 3331399465
    },
    "185": {
        "mgs_link": "/profile/22838",
        "score": "5839",
        "roblox_id": 1104357724
    },
    "186": {
        "mgs_link": "/profile/12644",
        "score": "5807",
        "roblox_id": 3517914
    },
    "187": {
        "mgs_link": "/profile/28515",
        "score": "5682",
        "roblox_id": 4191085590
    },
    "188": {
        "mgs_link": "/profile/15973",
        "score": "5440",
        "roblox_id": 193887129
    },
    "189": {
        "mgs_link": "/profile/31892",
        "score": "5239",
        "roblox_id": 3133120195
    },
    "190": {
        "mgs_link": "/profile/17307",
        "score": "5154",
        "roblox_id": 368979975
    },
    "191": {
        "mgs_link": "/profile/19373",
        "score": "5122",
        "roblox_id": 15019619
    },
    "192": {
        "mgs_link": "/profile/25591",
        "score": "5078",
        "roblox_id": 27962206
    },
    "193": {
        "mgs_link": "/profile/26859",
        "score": "5044",
        "roblox_id": 4651588901
    },
    "194": {
        "mgs_link": "/profile/26515",
        "score": "4961",
        "roblox_id": 3167238141
    },
    "195": {
        "mgs_link": "/profile/31156",
        "score": "4796",
        "roblox_id": 3977570701
    },
    "196": {
        "mgs_link": "",
        "score": "4776",
        "roblox_id": null
    },
    "197": {
        "mgs_link": "/profile/25767",
        "score": "4753",
        "roblox_id": 1181680
    },
    "198": {
        "mgs_link": "/profile/32351",
        "score": "4647",
        "roblox_id": 3115049281
    },
    "199": {
        "mgs_link": "/profile/30489",
        "score": "4443",
        "roblox_id": 52049784
    },
    "200": {
        "mgs_link": "/profile/27046",
        "score": "4402",
        "roblox_id": 2338999931
    },
    "201": {
        "mgs_link": "/profile/27786",
        "score": "4308",
        "roblox_id": 1684369107
    },
    "202": {
        "mgs_link": "/profile/15262",
        "score": "4295",
        "roblox_id": null
    },
    "203": {
        "mgs_link": "/profile/27553",
        "score": "4063",
        "roblox_id": 17479101
    },
    "204": {
        "mgs_link": "/profile/29320",
        "score": "4056",
        "roblox_id": 2773805440
    },
    "205": {
        "mgs_link": "/profile/31614",
        "score": "4043",
        "roblox_id": 4661381302
    },
    "206": {
        "mgs_link": "/profile/21780",
        "score": "4019",
        "roblox_id": 1668234823
    },
    "207": {
        "mgs_link": "/profile/29504",
        "score": "3940",
        "roblox_id": 3388255909
    },
    "208": {
        "mgs_link": "/profile/30104",
        "score": "3868",
        "roblox_id": 219543676
    },
    "209": {
        "mgs_link": "/profile/22828",
        "score": "3867",
        "roblox_id": 274794507
    },
    "210": {
        "mgs_link": "/profile/24610",
        "score": "3719",
        "roblox_id": 3816744386
    },
    "211": {
        "mgs_link": "/profile/31576",
        "score": "3615",
        "roblox_id": 19342270
    },
    "212": {
        "mgs_link": "/profile/34353",
        "score": "3519",
        "roblox_id": 617579488
    },
    "213": {
        "mgs_link": "/profile/31270",
        "score": "3474",
        "roblox_id": 1797828252
    },
    "214": {
        "mgs_link": "/profile/31457",
        "score": "3346",
        "roblox_id": 2545955395
    },
    "215": {
        "mgs_link": "/profile/31634",
        "score": "3287",
        "roblox_id": 2482834
    },
    "216": {
        "mgs_link": "/profile/32342",
        "score": "3275",
        "roblox_id": 116177658
    },
    "217": {
        "mgs_link": "/profile/27049",
        "score": "3262",
        "roblox_id": null
    },
    "218": {
        "mgs_link": "/profile/8508",
        "score": "3232",
        "roblox_id": 59403394
    },
    "219": {
        "mgs_link": "/profile/31251",
        "score": "3177",
        "roblox_id": 422082266
    },
    "220": {
        "mgs_link": "/profile/31353",
        "score": "3159",
        "roblox_id": 1845289142
    },
    "221": {
        "mgs_link": "/profile/32400",
        "score": "3004",
        "roblox_id": 1511314959
    },
    "222": {
        "mgs_link": "/profile/25321",
        "score": "2986",
        "roblox_id": 1123067675
    },
    "223": {
        "mgs_link": "",
        "score": "2973",
        "roblox_id": null
    },
    "224": {
        "mgs_link": "/profile/32792",
        "score": "2967",
        "roblox_id": 969947912
    },
    "225": {
        "mgs_link": "/profile/15981",
        "score": "2945",
        "roblox_id": 860955129
    },
    "226": {
        "mgs_link": "/profile/27924",
        "score": "2788",
        "roblox_id": 113688147
    },
    "227": {
        "mgs_link": "/profile/29670",
        "score": "2747",
        "roblox_id": 2623400103
    },
    "228": {
        "mgs_link": "/profile/32573",
        "score": "2623",
        "roblox_id": 547498991
    },
    "229": {
        "mgs_link": "/profile/27023",
        "score": "2587",
        "roblox_id": 2910782688
    },
    "230": {
        "mgs_link": "/profile/24933",
        "score": "2528",
        "roblox_id": null
    },
    "231": {
        "mgs_link": "/profile/23755",
        "score": "2475",
        "roblox_id": 139201954
    },
    "232": {
        "mgs_link": "/profile/27856",
        "score": "2448",
        "roblox_id": 4404017110
    },
    "233": {
        "mgs_link": "/profile/28721",
        "score": "2429",
        "roblox_id": 330190
    },
    "234": {
        "mgs_link": "/profile/16673",
        "score": "2422",
        "roblox_id": 14900529
    },
    "235": {
        "mgs_link": "/profile/21344",
        "score": "2331",
        "roblox_id": 9105133400
    },
    "236": {
        "mgs_link": "/pro/primal_r",
        "score": "2253",
        "roblox_id": null
    },
    "237": {
        "mgs_link": "/profile/23911",
        "score": "2240",
        "roblox_id": 108854612
    },
    "238": {
        "mgs_link": "/profile/14928",
        "score": "2142",
        "roblox_id": 1241116927
    },
    "239": {
        "mgs_link": "/profile/21433",
        "score": "2128",
        "roblox_id": 4597856474
    },
    "240": {
        "mgs_link": "/profile/17259",
        "score": "2107",
        "roblox_id": 7281619
    },
    "241": {
        "mgs_link": "/profile/29075",
        "score": "2106",
        "roblox_id": 4957041415
    },
    "242": {
        "mgs_link": "/profile/34260",
        "score": "2051",
        "roblox_id": 1837741519
    },
    "243": {
        "mgs_link": "",
        "score": "2006",
        "roblox_id": null
    },
    "244": {
        "mgs_link": "/profile/31178",
        "score": "1985",
        "roblox_id": 49271755
    },
    "245": {
        "mgs_link": "/profile/34020",
        "score": "1923",
        "roblox_id": null
    },
    "246": {
        "mgs_link": "/profile/24750",
        "score": "1883",
        "roblox_id": 2382094873
    },
    "247": {
        "mgs_link": "/profile/29474",
        "score": "1862",
        "roblox_id": 487562657
    },
    "248": {
        "mgs_link": "/profile/5395",
        "score": "1831",
        "roblox_id": 53583125
    },
    "249": {
        "mgs_link": "/profile/30307",
        "score": "1741",
        "roblox_id": 1191502130
    },
    "250": {
        "mgs_link": "/profile/25844",
        "score": "1734",
        "roblox_id": 171733112
    },
    "251": {
        "mgs_link": "/profile/34696",
        "score": "1660",
        "roblox_id": 9229703131
    },
    "252": {
        "mgs_link": "/profile/33929",
        "score": "1657",
        "roblox_id": 106911609
    },
    "253": {
        "mgs_link": "/profile/28683",
        "score": "1633",
        "roblox_id": 352881608
    },
    "254": {
        "mgs_link": "/profile/27088",
        "score": "1604",
        "roblox_id": 3776515050
    },
    "255": {
        "mgs_link": "/profile/32733",
        "score": "1541",
        "roblox_id": 973210555
    },
    "256": {
        "mgs_link": "/profile/26359",
        "score": "1471",
        "roblox_id": 709983896
    },
    "257": {
        "mgs_link": "/profile/12340",
        "score": "1419",
        "roblox_id": 2704802013
    },
    "258": {
        "mgs_link": "/profile/27836",
        "score": "1409",
        "roblox_id": 117135588
    },
    "259": {
        "mgs_link": "/profile/31677",
        "score": "1354",
        "roblox_id": 126179495
    },
    "260": {
        "mgs_link": "/profile/28854",
        "score": "1320",
        "roblox_id": 289321119
    },
    "261": {
        "mgs_link": "/profile/24379",
        "score": "1292",
        "roblox_id": 68403249
    },
    "262": {
        "mgs_link": "/profile/2361",
        "score": "1231",
        "roblox_id": 698598961
    },
    "263": {
        "mgs_link": "",
        "score": "1209",
        "roblox_id": null
    },
    "264": {
        "mgs_link": "/profile/33663",
        "score": "1158",
        "roblox_id": 1436822232
    },
    "265": {
        "mgs_link": "/profile/29499",
        "score": "1129",
        "roblox_id": 39345191
    },
    "266": {
        "mgs_link": "/profile/28137",
        "score": "1119",
        "roblox_id": 5328857795
    },
    "267": {
        "mgs_link": "/profile/1174",
        "score": "1100",
        "roblox_id": 273574268
    },
    "268": {
        "mgs_link": "/profile/33163",
        "score": "1095",
        "roblox_id": 2628402308
    },
    "269": {
        "mgs_link": "/profile/27539",
        "score": "1074",
        "roblox_id": 3495759140
    },
    "270": {
        "mgs_link": "/profile/28937",
        "score": "1042",
        "roblox_id": 2564003497
    },
    "271": {
        "mgs_link": "/profile/24896",
        "score": "1024",
        "roblox_id": 9130958406
    },
    "272": {
        "mgs_link": "/profile/29843",
        "score": "991",
        "roblox_id": 950017468
    },
    "273": {
        "mgs_link": "/profile/32603",
        "score": "961",
        "roblox_id": 2374154347
    },
    "274": {
        "mgs_link": "/profile/33693",
        "score": "946",
        "roblox_id": 304054167
    },
    "275": {
        "mgs_link": "/profile/26827",
        "score": "855",
        "roblox_id": 2663093957
    },
    "276": {
        "mgs_link": "/profile/23394",
        "score": "799",
        "roblox_id": 998244782
    },
    "277": {
        "mgs_link": "/profile/26765",
        "score": "779",
        "roblox_id": 1928828694
    },
    "278": {
        "mgs_link": "/profile/26959",
        "score": "767",
        "roblox_id": 1474127542
    },
    "279": {
        "mgs_link": "/profile/29588",
        "score": "698",
        "roblox_id": 144878301
    },
    "280": {
        "mgs_link": "/profile/3370",
        "score": "690",
        "roblox_id": 3727197945
    },
    "281": {
        "mgs_link": "/profile/23382",
        "score": "688",
        "roblox_id": 108888019
    },
    "282": {
        "mgs_link": "/profile/17529",
        "score": "682",
        "roblox_id": 5071479884
    },
    "283": {
        "mgs_link": "/profile/21923",
        "score": "645",
        "roblox_id": 76071882
    },
    "284": {
        "mgs_link": "/profile/11771",
        "score": "640",
        "roblox_id": 4767178869
    },
    "285": {
        "mgs_link": "/profile/30980",
        "score": "634",
        "roblox_id": 4674906102
    },
    "286": {
        "mgs_link": "/profile/12836",
        "score": "546",
        "roblox_id": 56703456
    },
    "287": {
        "mgs_link": "/profile/34339",
        "score": "531",
        "roblox_id": 2278283162
    },
    "288": {
        "mgs_link": "/profile/30677",
        "score": "513",
        "roblox_id": null
    },
    "289": {
        "mgs_link": "/profile/28139",
        "score": "501",
        "roblox_id": 488072198
    },
    "290": {
        "mgs_link": "/profile/29791",
        "score": "411",
        "roblox_id": 3552487440
    },
    "291": {
        "mgs_link": "/profile/28159",
        "score": "411",
        "roblox_id": 3552487440
    },
    "292": {
        "mgs_link": "",
        "score": "406",
        "roblox_id": null
    },
    "293": {
        "mgs_link": "/profile/29376",
        "score": "398",
        "roblox_id": 87870668
    },
    "294": {
        "mgs_link": "/profile/14899",
        "score": "392",
        "roblox_id": 2383109643
    },
    "295": {
        "mgs_link": "/profile/32184",
        "score": "379",
        "roblox_id": 7826118038
    },
    "296": {
        "mgs_link": "/profile/20234",
        "score": "376",
        "roblox_id": 155935885
    },
    "297": {
        "mgs_link": "/profile/24082",
        "score": "375",
        "roblox_id": 322274919
    },
    "298": {
        "mgs_link": "/profile/383",
        "score": "374",
        "roblox_id": 1344072910
    },
    "299": {
        "mgs_link": "/profile/30290",
        "score": "373",
        "roblox_id": 1366105927
    },
    "300": {
        "mgs_link": "/profile/30927",
        "score": "330",
        "roblox_id": 69555326
    },
    "301": {
        "mgs_link": "/profile/33187",
        "score": "310",
        "roblox_id": 2733668944
    },
    "302": {
        "mgs_link": "/profile/32305",
        "score": "293",
        "roblox_id": 21750121
    },
    "303": {
        "mgs_link": "/profile/30369",
        "score": "290",
        "roblox_id": null
    },
    "304": {
        "mgs_link": "/profile/28558",
        "score": "286",
        "roblox_id": 5135711156
    },
    "305": {
        "mgs_link": "/profile/31914",
        "score": "277",
        "roblox_id": 5135588584
    },
    "306": {
        "mgs_link": "/profile/34112",
        "score": "273",
        "roblox_id": 8982671827
    },
    "307": {
        "mgs_link": "/profile/32731",
        "score": "270",
        "roblox_id": 596350891
    },
    "308": {
        "mgs_link": "/profile/17071",
        "score": "270",
        "roblox_id": 2376395291
    },
    "309": {
        "mgs_link": "/profile/30382",
        "score": "265",
        "roblox_id": 5442403527
    },
    "310": {
        "mgs_link": "/profile/26695",
        "score": "257",
        "roblox_id": 1342778048
    },
    "311": {
        "mgs_link": "/profile/33011",
        "score": "256",
        "roblox_id": 97168428
    },
    "312": {
        "mgs_link": "/profile/29640",
        "score": "252",
        "roblox_id": 342848892
    },
    "313": {
        "mgs_link": "/profile/26759",
        "score": "248",
        "roblox_id": 3699826121
    },
    "314": {
        "mgs_link": "/profile/29878",
        "score": "235",
        "roblox_id": 470457483
    },
    "315": {
        "mgs_link": "/profile/30030",
        "score": "235",
        "roblox_id": 3570173476
    },
    "316": {
        "mgs_link": "/profile/30987",
        "score": "224",
        "roblox_id": 641337477
    },
    "317": {
        "mgs_link": "/profile/29475",
        "score": "221",
        "roblox_id": 22109218
    },
    "318": {
        "mgs_link": "/profile/24287",
        "score": "218",
        "roblox_id": 3646104917
    },
    "319": {
        "mgs_link": "/profile/24368",
        "score": "162",
        "roblox_id": 15759504
    },
    "320": {
        "mgs_link": "/profile/26735",
        "score": "150",
        "roblox_id": 4584047352
    },
    "321": {
        "mgs_link": "/profile/33469",
        "score": "149",
        "roblox_id": 7891865832
    },
    "322": {
        "mgs_link": "/profile/34182",
        "score": "146",
        "roblox_id": 3703801060
    },
    "323": {
        "mgs_link": "/pro/LordAvatarII",
        "score": "143",
        "roblox_id": 5468146434
    },
    "324": {
        "mgs_link": "/profile/34104",
        "score": "143",
        "roblox_id": 832230
    },
    "325": {
        "mgs_link": "/profile/8618",
        "score": "143",
        "roblox_id": 4990281043
    },
    "326": {
        "mgs_link": "/profile/31753",
        "score": "142",
        "roblox_id": 7531625634
    },
    "327": {
        "mgs_link": "/profile/31168",
        "score": "141",
        "roblox_id": 7639509458
    },
    "328": {
        "mgs_link": "/profile/26933",
        "score": "140",
        "roblox_id": 3206121588
    },
    "329": {
        "mgs_link": "/profile/625",
        "score": "137",
        "roblox_id": 88308203
    },
    "330": {
        "mgs_link": "/profile/28659",
        "score": "137",
        "roblox_id": 1826478106
    },
    "331": {
        "mgs_link": "/profile/31498",
        "score": "135",
        "roblox_id": 6180194698
    },
    "332": {
        "mgs_link": "/profile/34159",
        "score": "135",
        "roblox_id": 726509137
    },
    "333": {
        "mgs_link": "/profile/20518",
        "score": "134",
        "roblox_id": 2914044012
    },
    "334": {
        "mgs_link": "/profile/29300",
        "score": "133",
        "roblox_id": 89769179
    },
    "335": {
        "mgs_link": "/pro/SlyJosh",
        "score": "133",
        "roblox_id": 2019866417
    },
    "336": {
        "mgs_link": "/profile/12702",
        "score": "130",
        "roblox_id": 4007817780
    },
    "337": {
        "mgs_link": "/profile/33015",
        "score": "126",
        "roblox_id": 4985513002
    },
    "338": {
        "mgs_link": "/profile/16459",
        "score": "118",
        "roblox_id": 21122272
    },
    "339": {
        "mgs_link": "/profile/30569",
        "score": "118",
        "roblox_id": 2705855777
    },
    "340": {
        "mgs_link": "/profile/28279",
        "score": "104",
        "roblox_id": 116475224
    },
    "341": {
        "mgs_link": "/profile/27297",
        "score": "61",
        "roblox_id": 1787655593
    },
    "342": {
        "mgs_link": "/profile/24011",
        "score": "54",
        "roblox_id": 360825299
    },
    "343": {
        "mgs_link": "/profile/31244",
        "score": "46",
        "roblox_id": 1575000912
    },
    "344": {
        "mgs_link": "/profile/22202",
        "score": "44",
        "roblox_id": 54169502
    },
    "345": {
        "mgs_link": "/profile/28704",
        "score": "25",
        "roblox_id": 977452116
    },
    "346": {
        "mgs_link": "/profile/7196",
        "score": "2",
        "roblox_id": 131206895
    },
    "347": {
        "mgs_link": "/profile/25285",
        "score": "2",
        "roblox_id": 7248833543
    },
    "348": {
        "mgs_link": "/profile/33691",
        "score": "2",
        "roblox_id": 117802326
    }
}