{
    "1": {
        "mgs_link": "/profile/23187",
        "score": "31458939",
        "roblox_id": 29666286
    },
    "2": {
        "mgs_link": "/profile/31595",
        "score": "7784552",
        "roblox_id": 666358894
    },
    "3": {
        "mgs_link": "/profile/36060",
        "score": "6579145",
        "roblox_id": 452575648
    },
    "4": {
        "mgs_link": "/profile/17148",
        "score": "4846866",
        "roblox_id": 3396084431
    },
    "5": {
        "mgs_link": "/profile/31862",
        "score": "4613901",
        "roblox_id": 236280233
    },
    "6": {
        "mgs_link": "/profile/30721",
        "score": "3345233",
        "roblox_id": 841659250
    },
    "7": {
        "mgs_link": "/profile/34403",
        "score": "2881669",
        "roblox_id": 1079214051
    },
    "8": {
        "mgs_link": "/profile/34397",
        "score": "2761570",
        "roblox_id": 48565387
    },
    "9": {
        "mgs_link": "/profile/19425",
        "score": "2752508",
        "roblox_id": 3396114621
    },
    "10": {
        "mgs_link": "/profile/37035",
        "score": "2648315",
        "roblox_id": 586606773
    },
    "11": {
        "mgs_link": "/profile/36175",
        "score": "2611985",
        "roblox_id": 1733284890
    },
    "12": {
        "mgs_link": "/profile/29995",
        "score": "2606797",
        "roblox_id": 5178675
    },
    "13": {
        "mgs_link": "/profile/30722",
        "score": "2564165",
        "roblox_id": 157886048
    },
    "14": {
        "mgs_link": "/profile/25449",
        "score": "2512466",
        "roblox_id": 735344329
    },
    "15": {
        "mgs_link": "/profile/9819",
        "score": "2382464",
        "roblox_id": null
    },
    "16": {
        "mgs_link": "/profile/30570",
        "score": "2302278",
        "roblox_id": 1751807812
    },
    "17": {
        "mgs_link": "/profile/31735",
        "score": "2117131",
        "roblox_id": 662990666
    },
    "18": {
        "mgs_link": "/profile/24093",
        "score": "2043212",
        "roblox_id": null
    },
    "19": {
        "mgs_link": "/profile/30727",
        "score": "1995310",
        "roblox_id": 1018180079
    },
    "20": {
        "mgs_link": "/profile/29872",
        "score": "1967005",
        "roblox_id": 76417643
    },
    "21": {
        "mgs_link": "/profile/30723",
        "score": "1848290",
        "roblox_id": 1058908271
    },
    "22": {
        "mgs_link": "/profile/31320",
        "score": "1657723",
        "roblox_id": 639181236
    },
    "23": {
        "mgs_link": "/profile/31090",
        "score": "1590547",
        "roblox_id": 64664125
    },
    "24": {
        "mgs_link": "/profile/31657",
        "score": "1588586",
        "roblox_id": 418574311
    },
    "25": {
        "mgs_link": "/profile/31344",
        "score": "1554383",
        "roblox_id": 7837172285
    },
    "26": {
        "mgs_link": "/profile/27403",
        "score": "1461439",
        "roblox_id": 1196407759
    },
    "27": {
        "mgs_link": "/pro/Magnus77",
        "score": "1436317",
        "roblox_id": 4383738707
    },
    "28": {
        "mgs_link": "/profile/35740",
        "score": "1409500",
        "roblox_id": 1166878867
    },
    "29": {
        "mgs_link": "",
        "score": "1361151",
        "roblox_id": null
    },
    "30": {
        "mgs_link": "/profile/30767",
        "score": "1359668",
        "roblox_id": 406804391
    },
    "31": {
        "mgs_link": "",
        "score": "1286058",
        "roblox_id": null
    },
    "32": {
        "mgs_link": "/profile/31091",
        "score": "1267766",
        "roblox_id": null
    },
    "33": {
        "mgs_link": "/profile/27630",
        "score": "1263778",
        "roblox_id": 7908621
    },
    "34": {
        "mgs_link": "/profile/33569",
        "score": "1074003",
        "roblox_id": 43105067
    },
    "35": {
        "mgs_link": "/profile/35621",
        "score": "1051287",
        "roblox_id": 438476861
    },
    "36": {
        "mgs_link": "/profile/34402",
        "score": "1032780",
        "roblox_id": 1246584213
    },
    "37": {
        "mgs_link": "/profile/29303",
        "score": "994600",
        "roblox_id": 1837200789
    },
    "38": {
        "mgs_link": "/profile/30279",
        "score": "992909",
        "roblox_id": 14953929
    },
    "39": {
        "mgs_link": "/profile/34346",
        "score": "992007",
        "roblox_id": 2722467628
    },
    "40": {
        "mgs_link": "/profile/35625",
        "score": "987821",
        "roblox_id": 1835457724
    },
    "41": {
        "mgs_link": "/profile/36776",
        "score": "977755",
        "roblox_id": 1290723803
    },
    "42": {
        "mgs_link": "/profile/34580",
        "score": "967091",
        "roblox_id": 440183421
    },
    "43": {
        "mgs_link": "/profile/25781",
        "score": "957659",
        "roblox_id": 16972041
    },
    "44": {
        "mgs_link": "/profile/37074",
        "score": "941439",
        "roblox_id": 1114211748
    },
    "45": {
        "mgs_link": "/profile/31044",
        "score": "919833",
        "roblox_id": 597286023
    },
    "46": {
        "mgs_link": "/profile/31416",
        "score": "902511",
        "roblox_id": 96492309
    },
    "47": {
        "mgs_link": "/profile/27350",
        "score": "895330",
        "roblox_id": 391114511
    },
    "48": {
        "mgs_link": "/profile/33902",
        "score": "865999",
        "roblox_id": 1637470692
    },
    "49": {
        "mgs_link": "/profile/31738",
        "score": "864281",
        "roblox_id": 254693948
    },
    "50": {
        "mgs_link": "/profile/36300",
        "score": "828683",
        "roblox_id": 1582652250
    },
    "51": {
        "mgs_link": "/profile/29644",
        "score": "805271",
        "roblox_id": 34685319
    },
    "52": {
        "mgs_link": "/profile/38187",
        "score": "769736",
        "roblox_id": 2747433733
    },
    "53": {
        "mgs_link": "/profile/30766",
        "score": "762019",
        "roblox_id": 559989880
    },
    "54": {
        "mgs_link": "/profile/33483",
        "score": "759352",
        "roblox_id": 817133338
    },
    "55": {
        "mgs_link": "/profile/35815",
        "score": "754753",
        "roblox_id": 2039601190
    },
    "56": {
        "mgs_link": "/profile/37339",
        "score": "713557",
        "roblox_id": 139513913
    },
    "57": {
        "mgs_link": "/profile/32115",
        "score": "686517",
        "roblox_id": 1048708065
    },
    "58": {
        "mgs_link": "/profile/28780",
        "score": "686347",
        "roblox_id": 119404404
    },
    "59": {
        "mgs_link": "/profile/35197",
        "score": "686157",
        "roblox_id": 1071023887
    },
    "60": {
        "mgs_link": "/profile/29035",
        "score": "669466",
        "roblox_id": 372547153
    },
    "61": {
        "mgs_link": "",
        "score": "646695",
        "roblox_id": null
    },
    "62": {
        "mgs_link": "/profile/28087",
        "score": "634809",
        "roblox_id": 17900059
    },
    "63": {
        "mgs_link": "/profile/26705",
        "score": "621682",
        "roblox_id": 314794478
    },
    "64": {
        "mgs_link": "/profile/15444",
        "score": "599005",
        "roblox_id": null
    },
    "65": {
        "mgs_link": "/profile/8242",
        "score": "592004",
        "roblox_id": 15758354
    },
    "66": {
        "mgs_link": "/profile/28896",
        "score": "586183",
        "roblox_id": 74642833
    },
    "67": {
        "mgs_link": "/profile/27169",
        "score": "580939",
        "roblox_id": 2028070760
    },
    "68": {
        "mgs_link": "/profile/27553",
        "score": "580426",
        "roblox_id": 17479101
    },
    "69": {
        "mgs_link": "/profile/31676",
        "score": "559725",
        "roblox_id": 35433007
    },
    "70": {
        "mgs_link": "/profile/26706",
        "score": "549710",
        "roblox_id": 32456653
    },
    "71": {
        "mgs_link": "/profile/22468",
        "score": "538496",
        "roblox_id": 275180007
    },
    "72": {
        "mgs_link": "/profile/24814",
        "score": "530436",
        "roblox_id": 1946613959
    },
    "73": {
        "mgs_link": "/profile/35712",
        "score": "518125",
        "roblox_id": 185584169
    },
    "74": {
        "mgs_link": "/profile/31508",
        "score": "503143",
        "roblox_id": 2026532992
    },
    "75": {
        "mgs_link": "/profile/25452",
        "score": "495748",
        "roblox_id": 1927302226
    },
    "76": {
        "mgs_link": "/profile/35670",
        "score": "494263",
        "roblox_id": 1235877402
    },
    "77": {
        "mgs_link": "/profile/27633",
        "score": "479601",
        "roblox_id": 379343212
    },
    "78": {
        "mgs_link": "/profile/38354",
        "score": "478443",
        "roblox_id": 177707307
    },
    "79": {
        "mgs_link": "/profile/32083",
        "score": "466100",
        "roblox_id": 101598208
    },
    "80": {
        "mgs_link": "/profile/35383",
        "score": "465624",
        "roblox_id": 74634139
    },
    "81": {
        "mgs_link": "/profile/33933",
        "score": "461418",
        "roblox_id": 132441653
    },
    "82": {
        "mgs_link": "/profile/33901",
        "score": "453415",
        "roblox_id": 1619459034
    },
    "83": {
        "mgs_link": "/profile/36016",
        "score": "449312",
        "roblox_id": 1554840483
    },
    "84": {
        "mgs_link": "/profile/22838",
        "score": "449091",
        "roblox_id": 1104357724
    },
    "85": {
        "mgs_link": "/profile/37321",
        "score": "443128",
        "roblox_id": 2228749904
    },
    "86": {
        "mgs_link": "/profile/29816",
        "score": "433774",
        "roblox_id": 13078566
    },
    "87": {
        "mgs_link": "/profile/32723",
        "score": "417473",
        "roblox_id": 183574893
    },
    "88": {
        "mgs_link": "/profile/31542",
        "score": "415823",
        "roblox_id": 141113364
    },
    "89": {
        "mgs_link": "/profile/31902",
        "score": "411771",
        "roblox_id": 3392129146
    },
    "90": {
        "mgs_link": "/profile/36297",
        "score": "400785",
        "roblox_id": 620995087
    },
    "91": {
        "mgs_link": "/profile/29665",
        "score": "390571",
        "roblox_id": 62908718
    },
    "92": {
        "mgs_link": "/profile/36028",
        "score": "389041",
        "roblox_id": 214145024
    },
    "93": {
        "mgs_link": "/profile/26726",
        "score": "385263",
        "roblox_id": 1451793029
    },
    "94": {
        "mgs_link": "/profile/27646",
        "score": "375830",
        "roblox_id": 51264408
    },
    "95": {
        "mgs_link": "/profile/34740",
        "score": "373502",
        "roblox_id": 2241826191
    },
    "96": {
        "mgs_link": "/profile/29009",
        "score": "370649",
        "roblox_id": 534312431
    },
    "97": {
        "mgs_link": "/profile/32351",
        "score": "366971",
        "roblox_id": 3115049281
    },
    "98": {
        "mgs_link": "/profile/34442",
        "score": "365940",
        "roblox_id": 405894808
    },
    "99": {
        "mgs_link": "/profile/3231",
        "score": "362558",
        "roblox_id": 1790417412
    },
    "100": {
        "mgs_link": "/profile/21431",
        "score": "349088",
        "roblox_id": 30397528
    },
    "101": {
        "mgs_link": "/profile/28598",
        "score": "349036",
        "roblox_id": 116544395
    },
    "102": {
        "mgs_link": "/profile/21344",
        "score": "344660",
        "roblox_id": 9105133400
    },
    "103": {
        "mgs_link": "/profile/19485",
        "score": "342876",
        "roblox_id": 139816438
    },
    "104": {
        "mgs_link": "/profile/12040",
        "score": "330856",
        "roblox_id": 3222429
    },
    "105": {
        "mgs_link": "/profile/31664",
        "score": "330090",
        "roblox_id": 2417445371
    },
    "106": {
        "mgs_link": "/profile/6980",
        "score": "326094",
        "roblox_id": 119205656
    },
    "107": {
        "mgs_link": "/profile/3321",
        "score": "321449",
        "roblox_id": null
    },
    "108": {
        "mgs_link": "/profile/33187",
        "score": "320498",
        "roblox_id": 2733668944
    },
    "109": {
        "mgs_link": "/profile/34592",
        "score": "320433",
        "roblox_id": 133017244
    },
    "110": {
        "mgs_link": "/profile/28332",
        "score": "320308",
        "roblox_id": 909726918
    },
    "111": {
        "mgs_link": "",
        "score": "310731",
        "roblox_id": null
    },
    "112": {
        "mgs_link": "/profile/28893",
        "score": "308233",
        "roblox_id": 29722073
    },
    "113": {
        "mgs_link": "/profile/32089",
        "score": "303885",
        "roblox_id": 3788135066
    },
    "114": {
        "mgs_link": "/profile/21398",
        "score": "292711",
        "roblox_id": 6147383
    },
    "115": {
        "mgs_link": "/profile/21342",
        "score": "292492",
        "roblox_id": 45284010
    },
    "116": {
        "mgs_link": "/profile/26724",
        "score": "288800",
        "roblox_id": 121403165
    },
    "117": {
        "mgs_link": "/profile/36737",
        "score": "282159",
        "roblox_id": 135698878
    },
    "118": {
        "mgs_link": "/profile/25672",
        "score": "276274",
        "roblox_id": 126665405
    },
    "119": {
        "mgs_link": "/profile/36881",
        "score": "274315",
        "roblox_id": 1289509364
    },
    "120": {
        "mgs_link": "/profile/27158",
        "score": "271896",
        "roblox_id": 4213274
    },
    "121": {
        "mgs_link": "/profile/32141",
        "score": "270799",
        "roblox_id": 631474129
    },
    "122": {
        "mgs_link": "/profile/30786",
        "score": "269598",
        "roblox_id": 105233923
    },
    "123": {
        "mgs_link": "/profile/34722",
        "score": "265842",
        "roblox_id": 3838589116
    },
    "124": {
        "mgs_link": "/profile/28903",
        "score": "259812",
        "roblox_id": 106079243
    },
    "125": {
        "mgs_link": "/profile/27074",
        "score": "258265",
        "roblox_id": 73030226
    },
    "126": {
        "mgs_link": "/profile/29749",
        "score": "256524",
        "roblox_id": 73738796
    },
    "127": {
        "mgs_link": "/profile/28090",
        "score": "253920",
        "roblox_id": 69612662
    },
    "128": {
        "mgs_link": "/profile/27464",
        "score": "252805",
        "roblox_id": 1578564925
    },
    "129": {
        "mgs_link": "/profile/32523",
        "score": "241291",
        "roblox_id": 477579776
    },
    "130": {
        "mgs_link": "/profile/30621",
        "score": "241269",
        "roblox_id": null
    },
    "131": {
        "mgs_link": "/profile/25043",
        "score": "236626",
        "roblox_id": 1416885032
    },
    "132": {
        "mgs_link": "/profile/25887",
        "score": "234356",
        "roblox_id": 125045492
    },
    "133": {
        "mgs_link": "/profile/28306",
        "score": "233464",
        "roblox_id": 1262689461
    },
    "134": {
        "mgs_link": "/profile/31698",
        "score": "230785",
        "roblox_id": 55575362
    },
    "135": {
        "mgs_link": "/profile/27005",
        "score": "225690",
        "roblox_id": 461657385
    },
    "136": {
        "mgs_link": "/profile/17307",
        "score": "220117",
        "roblox_id": 368979975
    },
    "137": {
        "mgs_link": "/profile/31353",
        "score": "219621",
        "roblox_id": 1845289142
    },
    "138": {
        "mgs_link": "/profile/18167",
        "score": "215119",
        "roblox_id": 264258544
    },
    "139": {
        "mgs_link": "/profile/29731",
        "score": "211456",
        "roblox_id": 4331026
    },
    "140": {
        "mgs_link": "/profile/17434",
        "score": "211093",
        "roblox_id": 22674979
    },
    "141": {
        "mgs_link": "/profile/28561",
        "score": "207218",
        "roblox_id": 107748779
    },
    "142": {
        "mgs_link": "/profile/38415",
        "score": "206271",
        "roblox_id": null
    },
    "143": {
        "mgs_link": "/profile/29629",
        "score": "205670",
        "roblox_id": 459983273
    },
    "144": {
        "mgs_link": "/profile/11128",
        "score": "203580",
        "roblox_id": null
    },
    "145": {
        "mgs_link": "/profile/13083",
        "score": "200499",
        "roblox_id": 107354469
    },
    "146": {
        "mgs_link": "/profile/26522",
        "score": "193457",
        "roblox_id": 16251983
    },
    "147": {
        "mgs_link": "/profile/32166",
        "score": "192750",
        "roblox_id": 157696723
    },
    "148": {
        "mgs_link": "/profile/28600",
        "score": "192234",
        "roblox_id": 936079657
    },
    "149": {
        "mgs_link": "/profile/28515",
        "score": "191842",
        "roblox_id": 4191085590
    },
    "150": {
        "mgs_link": "/profile/26689",
        "score": "190872",
        "roblox_id": 68220680
    },
    "151": {
        "mgs_link": "/profile/31185",
        "score": "190224",
        "roblox_id": 10950770
    },
    "152": {
        "mgs_link": "/profile/36107",
        "score": "189779",
        "roblox_id": 1416560099
    },
    "153": {
        "mgs_link": "/profile/25511",
        "score": "189374",
        "roblox_id": 104759787
    },
    "154": {
        "mgs_link": "/profile/36469",
        "score": "189252",
        "roblox_id": 907492265
    },
    "155": {
        "mgs_link": "/profile/34000",
        "score": "188955",
        "roblox_id": 3755318470
    },
    "156": {
        "mgs_link": "/profile/28045",
        "score": "184749",
        "roblox_id": 234930053
    },
    "157": {
        "mgs_link": "/profile/29755",
        "score": "183138",
        "roblox_id": 1509600534
    },
    "158": {
        "mgs_link": "/profile/32384",
        "score": "182779",
        "roblox_id": 10469862
    },
    "159": {
        "mgs_link": "/profile/34401",
        "score": "181327",
        "roblox_id": 1207191776
    },
    "160": {
        "mgs_link": "/profile/27075",
        "score": "180753",
        "roblox_id": 41628835
    },
    "161": {
        "mgs_link": "/profile/35034",
        "score": "179925",
        "roblox_id": 3348862570
    },
    "162": {
        "mgs_link": "/profile/37380",
        "score": "179548",
        "roblox_id": null
    },
    "163": {
        "mgs_link": "/profile/34035",
        "score": "177784",
        "roblox_id": 2560262759
    },
    "164": {
        "mgs_link": "/profile/34676",
        "score": "176854",
        "roblox_id": 3534752556
    },
    "165": {
        "mgs_link": "/profile/31768",
        "score": "174666",
        "roblox_id": 969808254
    },
    "166": {
        "mgs_link": "/profile/25591",
        "score": "163447",
        "roblox_id": 27962206
    },
    "167": {
        "mgs_link": "/profile/34526",
        "score": "163331",
        "roblox_id": 929628703
    },
    "168": {
        "mgs_link": "/profile/25203",
        "score": "160775",
        "roblox_id": 77073632
    },
    "169": {
        "mgs_link": "/profile/35567",
        "score": "160399",
        "roblox_id": 142651106
    },
    "170": {
        "mgs_link": "/profile/33998",
        "score": "157052",
        "roblox_id": 2350853222
    },
    "171": {
        "mgs_link": "/profile/12644",
        "score": "156230",
        "roblox_id": 3517914
    },
    "172": {
        "mgs_link": "/profile/31814",
        "score": "155348",
        "roblox_id": 2210423641
    },
    "173": {
        "mgs_link": "/profile/22686",
        "score": "152454",
        "roblox_id": 3841880910
    },
    "174": {
        "mgs_link": "/profile/30396",
        "score": "145025",
        "roblox_id": 486004978
    },
    "175": {
        "mgs_link": "/profile/24264",
        "score": "144876",
        "roblox_id": 1388020652
    },
    "176": {
        "mgs_link": "/profile/24378",
        "score": "143574",
        "roblox_id": 159604389
    },
    "177": {
        "mgs_link": "/profile/34790",
        "score": "141666",
        "roblox_id": 44083417
    },
    "178": {
        "mgs_link": "/profile/25844",
        "score": "134716",
        "roblox_id": 171733112
    },
    "179": {
        "mgs_link": "/profile/28554",
        "score": "134512",
        "roblox_id": 1550291658
    },
    "180": {
        "mgs_link": "/profile/33024",
        "score": "134245",
        "roblox_id": 647616678
    },
    "181": {
        "mgs_link": "/profile/29025",
        "score": "133057",
        "roblox_id": 95514679
    },
    "182": {
        "mgs_link": "/profile/32453",
        "score": "131551",
        "roblox_id": 172526178
    },
    "183": {
        "mgs_link": "/profile/28775",
        "score": "130581",
        "roblox_id": 2378966576
    },
    "184": {
        "mgs_link": "/profile/29620",
        "score": "129171",
        "roblox_id": 4253271952
    },
    "185": {
        "mgs_link": "/profile/35653",
        "score": "128211",
        "roblox_id": 3556900443
    },
    "186": {
        "mgs_link": "/profile/31966",
        "score": "127622",
        "roblox_id": 4966499367
    },
    "187": {
        "mgs_link": "/profile/35029",
        "score": "125742",
        "roblox_id": 618962989
    },
    "188": {
        "mgs_link": "/profile/30138",
        "score": "122860",
        "roblox_id": 4613428845
    },
    "189": {
        "mgs_link": "/profile/1174",
        "score": "122305",
        "roblox_id": 273574268
    },
    "190": {
        "mgs_link": "/profile/38426",
        "score": "121233",
        "roblox_id": 694652242
    },
    "191": {
        "mgs_link": "/profile/31593",
        "score": "120090",
        "roblox_id": 100019857
    },
    "192": {
        "mgs_link": "/profile/29924",
        "score": "119946",
        "roblox_id": 697082407
    },
    "193": {
        "mgs_link": "/profile/22308",
        "score": "119660",
        "roblox_id": 227775444
    },
    "194": {
        "mgs_link": "/profile/37281",
        "score": "116870",
        "roblox_id": 76222929
    },
    "195": {
        "mgs_link": "/profile/32342",
        "score": "114908",
        "roblox_id": 116177658
    },
    "196": {
        "mgs_link": "/profile/31484",
        "score": "113323",
        "roblox_id": 89359807
    },
    "197": {
        "mgs_link": "/profile/32515",
        "score": "113170",
        "roblox_id": 2336725585
    },
    "198": {
        "mgs_link": "/profile/28576",
        "score": "110402",
        "roblox_id": 142173158
    },
    "199": {
        "mgs_link": "/profile/28597",
        "score": "108179",
        "roblox_id": 341567541
    },
    "200": {
        "mgs_link": "/profile/36135",
        "score": "106375",
        "roblox_id": null
    },
    "201": {
        "mgs_link": "/profile/30829",
        "score": "104983",
        "roblox_id": 3973170586
    },
    "202": {
        "mgs_link": "/profile/30116",
        "score": "102577",
        "roblox_id": 1566903128
    },
    "203": {
        "mgs_link": "/profile/36299",
        "score": "102554",
        "roblox_id": 1807210460
    },
    "204": {
        "mgs_link": "/profile/21903",
        "score": "101165",
        "roblox_id": 666747743
    },
    "205": {
        "mgs_link": "/profile/32947",
        "score": "101091",
        "roblox_id": 1535325798
    },
    "206": {
        "mgs_link": "/profile/31594",
        "score": "99988",
        "roblox_id": 37212930
    },
    "207": {
        "mgs_link": "",
        "score": "99385",
        "roblox_id": null
    },
    "208": {
        "mgs_link": "/pro/Juicypillow23",
        "score": "98953",
        "roblox_id": 8982671827
    },
    "209": {
        "mgs_link": "",
        "score": "98541",
        "roblox_id": null
    },
    "210": {
        "mgs_link": "/profile/10389",
        "score": "96591",
        "roblox_id": 21325619
    },
    "211": {
        "mgs_link": "/profile/35428",
        "score": "96159",
        "roblox_id": 1663934204
    },
    "212": {
        "mgs_link": "/profile/36427",
        "score": "95377",
        "roblox_id": 2747750702
    },
    "213": {
        "mgs_link": "/profile/26669",
        "score": "93504",
        "roblox_id": 319438417
    },
    "214": {
        "mgs_link": "/profile/22555",
        "score": "92189",
        "roblox_id": 7796642778
    },
    "215": {
        "mgs_link": "/profile/28374",
        "score": "90962",
        "roblox_id": 230816847
    },
    "216": {
        "mgs_link": "/profile/27088",
        "score": "90104",
        "roblox_id": 3776515050
    },
    "217": {
        "mgs_link": "/profile/33626",
        "score": "89882",
        "roblox_id": 761198898
    },
    "218": {
        "mgs_link": "/profile/28615",
        "score": "89854",
        "roblox_id": 685485707
    },
    "219": {
        "mgs_link": "/profile/5668",
        "score": "89112",
        "roblox_id": 689765251
    },
    "220": {
        "mgs_link": "/profile/36935",
        "score": "87571",
        "roblox_id": 102356458
    },
    "221": {
        "mgs_link": "/profile/19367",
        "score": "87138",
        "roblox_id": 97220890
    },
    "222": {
        "mgs_link": "/profile/29499",
        "score": "86946",
        "roblox_id": 39345191
    },
    "223": {
        "mgs_link": "/profile/27004",
        "score": "86258",
        "roblox_id": 130489002
    },
    "224": {
        "mgs_link": "/profile/34643",
        "score": "85872",
        "roblox_id": 3388820946
    },
    "225": {
        "mgs_link": "/profile/36264",
        "score": "85474",
        "roblox_id": 492947281
    },
    "226": {
        "mgs_link": "/profile/37349",
        "score": "84996",
        "roblox_id": 2428353720
    },
    "227": {
        "mgs_link": "/profile/33878",
        "score": "83486",
        "roblox_id": 5648942107
    },
    "228": {
        "mgs_link": "/profile/32623",
        "score": "79297",
        "roblox_id": 721024447
    },
    "229": {
        "mgs_link": "/profile/35287",
        "score": "79085",
        "roblox_id": 8570420146
    },
    "230": {
        "mgs_link": "/profile/25767",
        "score": "78982",
        "roblox_id": 1181680
    },
    "231": {
        "mgs_link": "/profile/36612",
        "score": "77838",
        "roblox_id": null
    },
    "232": {
        "mgs_link": "/profile/17529",
        "score": "76107",
        "roblox_id": 5071479884
    },
    "233": {
        "mgs_link": "/profile/30475",
        "score": "74154",
        "roblox_id": 19376569
    },
    "234": {
        "mgs_link": "/profile/31576",
        "score": "73283",
        "roblox_id": 19342270
    },
    "235": {
        "mgs_link": "/profile/32400",
        "score": "72410",
        "roblox_id": 1511314959
    },
    "236": {
        "mgs_link": "/profile/36351",
        "score": "71621",
        "roblox_id": 1530643943
    },
    "237": {
        "mgs_link": "/profile/36647",
        "score": "70639",
        "roblox_id": 7459097577
    },
    "238": {
        "mgs_link": "/profile/34472",
        "score": "69919",
        "roblox_id": 1316273181
    },
    "239": {
        "mgs_link": "/profile/28035",
        "score": "69852",
        "roblox_id": 639943062
    },
    "240": {
        "mgs_link": "/profile/30937",
        "score": "69300",
        "roblox_id": 1563917241
    },
    "241": {
        "mgs_link": "/profile/37309",
        "score": "68425",
        "roblox_id": 10784284124
    },
    "242": {
        "mgs_link": "/profile/29771",
        "score": "67877",
        "roblox_id": 3336500555
    },
    "243": {
        "mgs_link": "/profile/31178",
        "score": "67739",
        "roblox_id": 49271755
    },
    "244": {
        "mgs_link": "/profile/26341",
        "score": "66280",
        "roblox_id": 185308795
    },
    "245": {
        "mgs_link": "/profile/23291",
        "score": "65981",
        "roblox_id": 134048330
    },
    "246": {
        "mgs_link": "/profile/26508",
        "score": "65809",
        "roblox_id": 413938595
    },
    "247": {
        "mgs_link": "/profile/27917",
        "score": "65642",
        "roblox_id": 104952427
    },
    "248": {
        "mgs_link": "/profile/29126",
        "score": "65620",
        "roblox_id": 174716109
    },
    "249": {
        "mgs_link": "/profile/31591",
        "score": "64903",
        "roblox_id": null
    },
    "250": {
        "mgs_link": "/profile/29840",
        "score": "64507",
        "roblox_id": 168337801
    },
    "251": {
        "mgs_link": "/profile/28599",
        "score": "63425",
        "roblox_id": 377811759
    },
    "252": {
        "mgs_link": "/profile/29671",
        "score": "62404",
        "roblox_id": 2409427960
    },
    "253": {
        "mgs_link": "/profile/12638",
        "score": "61767",
        "roblox_id": 3834304156
    },
    "254": {
        "mgs_link": "/profile/35060",
        "score": "61652",
        "roblox_id": null
    },
    "255": {
        "mgs_link": "/profile/30489",
        "score": "58539",
        "roblox_id": 52049784
    },
    "256": {
        "mgs_link": "/profile/26493",
        "score": "54724",
        "roblox_id": 1015066556
    },
    "257": {
        "mgs_link": "/profile/26070",
        "score": "53897",
        "roblox_id": 9307878
    },
    "258": {
        "mgs_link": "/profile/23585",
        "score": "53561",
        "roblox_id": 82397388
    },
    "259": {
        "mgs_link": "/profile/33929",
        "score": "53006",
        "roblox_id": 106911609
    },
    "260": {
        "mgs_link": "/profile/30183",
        "score": "51828",
        "roblox_id": 801812922
    },
    "261": {
        "mgs_link": "/profile/24896",
        "score": "51528",
        "roblox_id": 9130958406
    },
    "262": {
        "mgs_link": "/profile/31156",
        "score": "50270",
        "roblox_id": 3977570701
    },
    "263": {
        "mgs_link": "/profile/19373",
        "score": "50023",
        "roblox_id": 15019619
    },
    "264": {
        "mgs_link": "/profile/33163",
        "score": "49627",
        "roblox_id": 2628402308
    },
    "265": {
        "mgs_link": "/profile/29084",
        "score": "49078",
        "roblox_id": 237595971
    },
    "266": {
        "mgs_link": "/profile/32997",
        "score": "48255",
        "roblox_id": 8076708046
    },
    "267": {
        "mgs_link": "/profile/35936",
        "score": "48150",
        "roblox_id": 296669562
    },
    "268": {
        "mgs_link": "/profile/32733",
        "score": "46820",
        "roblox_id": 973210555
    },
    "269": {
        "mgs_link": "/profile/27786",
        "score": "45120",
        "roblox_id": 1684369107
    },
    "270": {
        "mgs_link": "/profile/31572",
        "score": "44070",
        "roblox_id": 129669819
    },
    "271": {
        "mgs_link": "/profile/37241",
        "score": "43264",
        "roblox_id": 181647033
    },
    "272": {
        "mgs_link": "/profile/31892",
        "score": "43107",
        "roblox_id": 3133120195
    },
    "273": {
        "mgs_link": "/profile/22828",
        "score": "43045",
        "roblox_id": 274794507
    },
    "274": {
        "mgs_link": "/profile/30307",
        "score": "42519",
        "roblox_id": 1191502130
    },
    "275": {
        "mgs_link": "/profile/35576",
        "score": "41730",
        "roblox_id": 2545137698
    },
    "276": {
        "mgs_link": "/profile/31548",
        "score": "41399",
        "roblox_id": 1134718984
    },
    "277": {
        "mgs_link": "/profile/23296",
        "score": "41226",
        "roblox_id": 49445602
    },
    "278": {
        "mgs_link": "/profile/15973",
        "score": "40934",
        "roblox_id": 193887129
    },
    "279": {
        "mgs_link": "/profile/36791",
        "score": "40794",
        "roblox_id": 570456
    },
    "280": {
        "mgs_link": "/profile/29320",
        "score": "40790",
        "roblox_id": 2773805440
    },
    "281": {
        "mgs_link": "/profile/31677",
        "score": "40759",
        "roblox_id": 126179495
    },
    "282": {
        "mgs_link": "/profile/30838",
        "score": "40359",
        "roblox_id": 7350299486
    },
    "283": {
        "mgs_link": "/profile/14899",
        "score": "39433",
        "roblox_id": 2383109643
    },
    "284": {
        "mgs_link": "/profile/34020",
        "score": "39156",
        "roblox_id": null
    },
    "285": {
        "mgs_link": "/profile/26827",
        "score": "39036",
        "roblox_id": 2663093957
    },
    "286": {
        "mgs_link": "/profile/29504",
        "score": "38682",
        "roblox_id": 3388255909
    },
    "287": {
        "mgs_link": "/profile/25789",
        "score": "38640",
        "roblox_id": 1276906588
    },
    "288": {
        "mgs_link": "/profile/24181",
        "score": "38148",
        "roblox_id": 3361194952
    },
    "289": {
        "mgs_link": "/profile/28728",
        "score": "38057",
        "roblox_id": 997169479
    },
    "290": {
        "mgs_link": "/profile/24610",
        "score": "37525",
        "roblox_id": 3816744386
    },
    "291": {
        "mgs_link": "/profile/24287",
        "score": "37030",
        "roblox_id": 3646104917
    },
    "292": {
        "mgs_link": "/profile/24493",
        "score": "36117",
        "roblox_id": 106620033
    },
    "293": {
        "mgs_link": "/profile/14928",
        "score": "34935",
        "roblox_id": 1241116927
    },
    "294": {
        "mgs_link": "/profile/21815",
        "score": "34418",
        "roblox_id": 86639063
    },
    "295": {
        "mgs_link": "/profile/28717",
        "score": "34386",
        "roblox_id": 1134337211
    },
    "296": {
        "mgs_link": "",
        "score": "33610",
        "roblox_id": null
    },
    "297": {
        "mgs_link": "/profile/26582",
        "score": "33170",
        "roblox_id": 463758443
    },
    "298": {
        "mgs_link": "/profile/34769",
        "score": "33076",
        "roblox_id": 5485812936
    },
    "299": {
        "mgs_link": "/profile/34260",
        "score": "32809",
        "roblox_id": 1837741519
    },
    "300": {
        "mgs_link": "/profile/31634",
        "score": "32510",
        "roblox_id": 2482834
    },
    "301": {
        "mgs_link": "/profile/30104",
        "score": "31952",
        "roblox_id": 219543676
    },
    "302": {
        "mgs_link": "/profile/28721",
        "score": "31659",
        "roblox_id": 330190
    },
    "303": {
        "mgs_link": "",
        "score": "31542",
        "roblox_id": null
    },
    "304": {
        "mgs_link": "/profile/27023",
        "score": "31215",
        "roblox_id": 2910782688
    },
    "305": {
        "mgs_link": "/profile/625",
        "score": "31157",
        "roblox_id": 88308203
    },
    "306": {
        "mgs_link": "/profile/33663",
        "score": "30183",
        "roblox_id": 1436822232
    },
    "307": {
        "mgs_link": "/profile/31270",
        "score": "30001",
        "roblox_id": 1797828252
    },
    "308": {
        "mgs_link": "/profile/34339",
        "score": "29043",
        "roblox_id": 2278283162
    },
    "309": {
        "mgs_link": "/profile/26516",
        "score": "28622",
        "roblox_id": 3331399465
    },
    "310": {
        "mgs_link": "/profile/32573",
        "score": "27466",
        "roblox_id": 547498991
    },
    "311": {
        "mgs_link": "/profile/26359",
        "score": "27325",
        "roblox_id": 709983896
    },
    "312": {
        "mgs_link": "/profile/29670",
        "score": "27015",
        "roblox_id": 2623400103
    },
    "313": {
        "mgs_link": "/profile/23755",
        "score": "26784",
        "roblox_id": 139201954
    },
    "314": {
        "mgs_link": "/profile/21780",
        "score": "26615",
        "roblox_id": 1668234823
    },
    "315": {
        "mgs_link": "/profile/8099",
        "score": "26446",
        "roblox_id": 7161518434
    },
    "316": {
        "mgs_link": "/profile/35786",
        "score": "26225",
        "roblox_id": 3402743893
    },
    "317": {
        "mgs_link": "/profile/11563",
        "score": "26149",
        "roblox_id": null
    },
    "318": {
        "mgs_link": "/profile/31457",
        "score": "25724",
        "roblox_id": 2545955395
    },
    "319": {
        "mgs_link": "/profile/30369",
        "score": "25543",
        "roblox_id": null
    },
    "320": {
        "mgs_link": "/profile/27924",
        "score": "25436",
        "roblox_id": 113688147
    },
    "321": {
        "mgs_link": "/profile/31251",
        "score": "24536",
        "roblox_id": 422082266
    },
    "322": {
        "mgs_link": "/profile/34997",
        "score": "23429",
        "roblox_id": 105966237
    },
    "323": {
        "mgs_link": "/profile/24379",
        "score": "22452",
        "roblox_id": 68403249
    },
    "324": {
        "mgs_link": "/profile/31614",
        "score": "21741",
        "roblox_id": 4661381302
    },
    "325": {
        "mgs_link": "/profile/35471",
        "score": "21305",
        "roblox_id": 9043532761
    },
    "326": {
        "mgs_link": "/profile/29075",
        "score": "21292",
        "roblox_id": 4957041415
    },
    "327": {
        "mgs_link": "/profile/28776",
        "score": "21282",
        "roblox_id": 3743827352
    },
    "328": {
        "mgs_link": "/profile/28159",
        "score": "20925",
        "roblox_id": 3552487440
    },
    "329": {
        "mgs_link": "/profile/36453",
        "score": "20901",
        "roblox_id": null
    },
    "330": {
        "mgs_link": "/profile/32603",
        "score": "20557",
        "roblox_id": 2374154347
    },
    "331": {
        "mgs_link": "/profile/15981",
        "score": "20380",
        "roblox_id": 860955129
    },
    "332": {
        "mgs_link": "/profile/23911",
        "score": "20163",
        "roblox_id": 108854612
    },
    "333": {
        "mgs_link": "",
        "score": "19914",
        "roblox_id": null
    },
    "334": {
        "mgs_link": "/profile/20518",
        "score": "19804",
        "roblox_id": 2914044012
    },
    "335": {
        "mgs_link": "/profile/29791",
        "score": "19550",
        "roblox_id": 3552487440
    },
    "336": {
        "mgs_link": "/profile/16673",
        "score": "19092",
        "roblox_id": 14900529
    },
    "337": {
        "mgs_link": "/profile/38428",
        "score": "18839",
        "roblox_id": 2399026335
    },
    "338": {
        "mgs_link": "/profile/27046",
        "score": "17763",
        "roblox_id": 2338999931
    },
    "339": {
        "mgs_link": "/profile/8508",
        "score": "17607",
        "roblox_id": 59403394
    },
    "340": {
        "mgs_link": "/profile/30927",
        "score": "17306",
        "roblox_id": 69555326
    },
    "341": {
        "mgs_link": "/profile/36262",
        "score": "17274",
        "roblox_id": 3220347166
    },
    "342": {
        "mgs_link": "/profile/27092",
        "score": "17263",
        "roblox_id": 106435459
    },
    "343": {
        "mgs_link": "/profile/24011",
        "score": "17217",
        "roblox_id": 360825299
    },
    "344": {
        "mgs_link": "/profile/32184",
        "score": "17146",
        "roblox_id": 7826118038
    },
    "345": {
        "mgs_link": "/profile/31103",
        "score": "15976",
        "roblox_id": 1376639215
    },
    "346": {
        "mgs_link": "/profile/22202",
        "score": "14517",
        "roblox_id": 54169502
    },
    "347": {
        "mgs_link": "/profile/35671",
        "score": "13732",
        "roblox_id": 98773318
    },
    "348": {
        "mgs_link": "/profile/12836",
        "score": "13721",
        "roblox_id": 56703456
    },
    "349": {
        "mgs_link": "/profile/27297",
        "score": "13393",
        "roblox_id": 1787655593
    },
    "350": {
        "mgs_link": "/profile/28659",
        "score": "13338",
        "roblox_id": 1826478106
    },
    "351": {
        "mgs_link": "/profile/36012",
        "score": "13174",
        "roblox_id": 105820899
    },
    "352": {
        "mgs_link": "/profile/31558",
        "score": "13144",
        "roblox_id": 1290589556
    },
    "353": {
        "mgs_link": "/profile/24750",
        "score": "12484",
        "roblox_id": 2382094873
    },
    "354": {
        "mgs_link": "/profile/24825",
        "score": "12306",
        "roblox_id": 21711375
    },
    "355": {
        "mgs_link": "/profile/28937",
        "score": "12168",
        "roblox_id": 2564003497
    },
    "356": {
        "mgs_link": "/profile/26719",
        "score": "11709",
        "roblox_id": 1406286539
    },
    "357": {
        "mgs_link": "/profile/24082",
        "score": "11648",
        "roblox_id": 322274919
    },
    "358": {
        "mgs_link": "",
        "score": "10291",
        "roblox_id": null
    },
    "359": {
        "mgs_link": "/profile/20234",
        "score": "10235",
        "roblox_id": 155935885
    },
    "360": {
        "mgs_link": "/profile/2361",
        "score": "10066",
        "roblox_id": 698598961
    },
    "361": {
        "mgs_link": "",
        "score": "9986",
        "roblox_id": null
    },
    "362": {
        "mgs_link": "/profile/25285",
        "score": "9662",
        "roblox_id": 7248833543
    },
    "363": {
        "mgs_link": "/profile/22691",
        "score": "9392",
        "roblox_id": 2611907837
    },
    "364": {
        "mgs_link": "/profile/6465",
        "score": "9351",
        "roblox_id": 1425157461
    },
    "365": {
        "mgs_link": "/profile/12340",
        "score": "9307",
        "roblox_id": 2704802013
    },
    "366": {
        "mgs_link": "/profile/7196",
        "score": "9218",
        "roblox_id": 131206895
    },
    "367": {
        "mgs_link": "/profile/32305",
        "score": "9029",
        "roblox_id": 21750121
    },
    "368": {
        "mgs_link": "/profile/34104",
        "score": "8808",
        "roblox_id": 832230
    },
    "369": {
        "mgs_link": "/profile/34696",
        "score": "8542",
        "roblox_id": 9229703131
    },
    "370": {
        "mgs_link": "/profile/21740",
        "score": "8517",
        "roblox_id": 10767439138
    },
    "371": {
        "mgs_link": "/profile/19360",
        "score": "7918",
        "roblox_id": 4941968879
    },
    "372": {
        "mgs_link": "/profile/24527",
        "score": "7738",
        "roblox_id": 628654824
    },
    "373": {
        "mgs_link": "/profile/29475",
        "score": "7371",
        "roblox_id": 22109218
    },
    "374": {
        "mgs_link": "/profile/23382",
        "score": "6864",
        "roblox_id": 108888019
    },
    "375": {
        "mgs_link": "/profile/30030",
        "score": "6751",
        "roblox_id": 3570173476
    },
    "376": {
        "mgs_link": "/profile/36271",
        "score": "6455",
        "roblox_id": 10092651644
    },
    "377": {
        "mgs_link": "/profile/29640",
        "score": "6439",
        "roblox_id": 342848892
    },
    "378": {
        "mgs_link": "/profile/829",
        "score": "6360",
        "roblox_id": 314571299
    },
    "379": {
        "mgs_link": "/profile/880",
        "score": "6282",
        "roblox_id": 1058329487
    },
    "380": {
        "mgs_link": "/profile/30677",
        "score": "6152",
        "roblox_id": null
    },
    "381": {
        "mgs_link": "/profile/29588",
        "score": "6095",
        "roblox_id": 144878301
    },
    "382": {
        "mgs_link": "/profile/27539",
        "score": "5919",
        "roblox_id": 3495759140
    },
    "383": {
        "mgs_link": "/profile/27430",
        "score": "5875",
        "roblox_id": 4067935907
    },
    "384": {
        "mgs_link": "/profile/383",
        "score": "5818",
        "roblox_id": 1344072910
    },
    "385": {
        "mgs_link": "/profile/28683",
        "score": "5566",
        "roblox_id": 352881608
    },
    "386": {
        "mgs_link": "/profile/33669",
        "score": "5481",
        "roblox_id": 9319158469
    },
    "387": {
        "mgs_link": "/profile/37385",
        "score": "5188",
        "roblox_id": 10679679377
    },
    "388": {
        "mgs_link": "/profile/33011",
        "score": "5132",
        "roblox_id": 97168428
    },
    "389": {
        "mgs_link": "",
        "score": "5058",
        "roblox_id": null
    },
    "390": {
        "mgs_link": "/profile/34353",
        "score": "5037",
        "roblox_id": 617579488
    },
    "391": {
        "mgs_link": "/profile/26933",
        "score": "4977",
        "roblox_id": 3206121588
    },
    "392": {
        "mgs_link": "/profile/29474",
        "score": "4956",
        "roblox_id": 487562657
    },
    "393": {
        "mgs_link": "/profile/21923",
        "score": "4901",
        "roblox_id": 76071882
    },
    "394": {
        "mgs_link": "/profile/28139",
        "score": "4899",
        "roblox_id": 488072198
    },
    "395": {
        "mgs_link": "/profile/3370",
        "score": "4704",
        "roblox_id": 3727197945
    },
    "396": {
        "mgs_link": "/profile/21433",
        "score": "4659",
        "roblox_id": 4597856474
    },
    "397": {
        "mgs_link": "/profile/28967",
        "score": "4164",
        "roblox_id": 751941390
    },
    "398": {
        "mgs_link": "/profile/34159",
        "score": "4108",
        "roblox_id": 726509137
    },
    "399": {
        "mgs_link": "/profile/30290",
        "score": "3831",
        "roblox_id": 1366105927
    },
    "400": {
        "mgs_link": "/profile/5395",
        "score": "3800",
        "roblox_id": 53583125
    },
    "401": {
        "mgs_link": "/profile/30862",
        "score": "3796",
        "roblox_id": 144146538
    },
    "402": {
        "mgs_link": "/profile/33691",
        "score": "3749",
        "roblox_id": 117802326
    },
    "403": {
        "mgs_link": "/profile/30987",
        "score": "3740",
        "roblox_id": 641337477
    },
    "404": {
        "mgs_link": "/profile/27856",
        "score": "3704",
        "roblox_id": 4404017110
    },
    "405": {
        "mgs_link": "/profile/103",
        "score": "3655",
        "roblox_id": 3564747294
    },
    "406": {
        "mgs_link": "/profile/26859",
        "score": "3489",
        "roblox_id": 4651588901
    },
    "407": {
        "mgs_link": "/profile/28279",
        "score": "3311",
        "roblox_id": 116475224
    },
    "408": {
        "mgs_link": "/profile/29376",
        "score": "3276",
        "roblox_id": 87870668
    },
    "409": {
        "mgs_link": "/profile/28854",
        "score": "3259",
        "roblox_id": 289321119
    },
    "410": {
        "mgs_link": "/profile/31498",
        "score": "3178",
        "roblox_id": 6180194698
    },
    "411": {
        "mgs_link": "/profile/27836",
        "score": "3146",
        "roblox_id": 117135588
    },
    "412": {
        "mgs_link": "/profile/16459",
        "score": "3111",
        "roblox_id": 21122272
    },
    "413": {
        "mgs_link": "/profile/29878",
        "score": "2876",
        "roblox_id": 470457483
    },
    "414": {
        "mgs_link": "/profile/33015",
        "score": "2812",
        "roblox_id": 4985513002
    },
    "415": {
        "mgs_link": "/profile/12946",
        "score": "2738",
        "roblox_id": 15324497
    },
    "416": {
        "mgs_link": "/profile/31132",
        "score": "2510",
        "roblox_id": 201285715
    },
    "417": {
        "mgs_link": "/profile/28558",
        "score": "2427",
        "roblox_id": 5135711156
    },
    "418": {
        "mgs_link": "/profile/27741",
        "score": "2270",
        "roblox_id": 8931294230
    },
    "419": {
        "mgs_link": "/profile/30569",
        "score": "2227",
        "roblox_id": 2705855777
    },
    "420": {
        "mgs_link": "/profile/31065",
        "score": "2000",
        "roblox_id": 1544
    },
    "421": {
        "mgs_link": "/profile/26695",
        "score": "1924",
        "roblox_id": 1342778048
    },
    "422": {
        "mgs_link": "/profile/12702",
        "score": "1873",
        "roblox_id": 4007817780
    },
    "423": {
        "mgs_link": "/profile/28137",
        "score": "1788",
        "roblox_id": 5328857795
    },
    "424": {
        "mgs_link": "/profile/24214",
        "score": "1753",
        "roblox_id": null
    },
    "425": {
        "mgs_link": "/profile/31914",
        "score": "1752",
        "roblox_id": 5135588584
    },
    "426": {
        "mgs_link": "/profile/31195",
        "score": "1667",
        "roblox_id": 3148760129
    },
    "427": {
        "mgs_link": "/profile/32731",
        "score": "1562",
        "roblox_id": 596350891
    },
    "428": {
        "mgs_link": "/profile/23394",
        "score": "1560",
        "roblox_id": 998244782
    },
    "429": {
        "mgs_link": "/profile/17200",
        "score": "1481",
        "roblox_id": 9303089734
    },
    "430": {
        "mgs_link": "/profile/29941",
        "score": "1392",
        "roblox_id": 87290246
    },
    "431": {
        "mgs_link": "/profile/32792",
        "score": "1385",
        "roblox_id": 969947912
    },
    "432": {
        "mgs_link": "/profile/31753",
        "score": "1341",
        "roblox_id": 7531625634
    },
    "433": {
        "mgs_link": "/profile/27802",
        "score": "1288",
        "roblox_id": 1823897750
    },
    "434": {
        "mgs_link": "/profile/14349",
        "score": "1231",
        "roblox_id": 5090540032
    },
    "435": {
        "mgs_link": "/profile/33469",
        "score": "1204",
        "roblox_id": 7891865832
    },
    "436": {
        "mgs_link": "/profile/11771",
        "score": "1140",
        "roblox_id": 4767178869
    },
    "437": {
        "mgs_link": "/profile/23796",
        "score": "1134",
        "roblox_id": 5631197537
    },
    "438": {
        "mgs_link": "/profile/30326",
        "score": "937",
        "roblox_id": 10794092151
    },
    "439": {
        "mgs_link": "/profile/26959",
        "score": "929",
        "roblox_id": 1474127542
    },
    "440": {
        "mgs_link": "/profile/34182",
        "score": "835",
        "roblox_id": 3703801060
    },
    "441": {
        "mgs_link": "/profile/30980",
        "score": "783",
        "roblox_id": 4674906102
    },
    "442": {
        "mgs_link": "/profile/33693",
        "score": "782",
        "roblox_id": 304054167
    },
    "443": {
        "mgs_link": "/profile/31279",
        "score": "762",
        "roblox_id": null
    },
    "444": {
        "mgs_link": "/profile/27524",
        "score": "754",
        "roblox_id": 5683636233
    },
    "445": {
        "mgs_link": "/profile/30382",
        "score": "655",
        "roblox_id": 5442403527
    },
    "446": {
        "mgs_link": "",
        "score": "603",
        "roblox_id": null
    },
    "447": {
        "mgs_link": "/profile/31547",
        "score": "470",
        "roblox_id": 2296102857
    },
    "448": {
        "mgs_link": "/profile/33581",
        "score": "436",
        "roblox_id": 3497346651
    },
    "449": {
        "mgs_link": "/profile/24933",
        "score": "380",
        "roblox_id": null
    },
    "450": {
        "mgs_link": "/pro/SlyJosh",
        "score": "333",
        "roblox_id": 2019866417
    },
    "451": {
        "mgs_link": "/profile/31168",
        "score": "318",
        "roblox_id": 7639509458
    },
    "452": {
        "mgs_link": "/profile/38212",
        "score": "308",
        "roblox_id": 8750556590
    },
    "453": {
        "mgs_link": "/profile/35348",
        "score": "179",
        "roblox_id": 60898302
    },
    "454": {
        "mgs_link": "/pro/LordAvatarII",
        "score": "142",
        "roblox_id": 5468146434
    },
    "455": {
        "mgs_link": "/profile/24900",
        "score": "99",
        "roblox_id": 2582608237
    },
    "456": {
        "mgs_link": "/profile/24368",
        "score": "96",
        "roblox_id": 15759504
    },
    "457": {
        "mgs_link": "/profile/31244",
        "score": "61",
        "roblox_id": 1575000912
    },
    "458": {
        "mgs_link": "/profile/33199",
        "score": "57",
        "roblox_id": 171037810
    },
    "459": {
        "mgs_link": "/profile/30646",
        "score": "54",
        "roblox_id": 4601721175
    }
}